GooglePatents/API.py
GooglePatents/GooglePatentsAPI.py
GooglePatents/__init__.py
GooglePatents-0.0.3.dist-info/LICENSE
GooglePatents-0.0.3.dist-info/METADATA
GooglePatents-0.0.3.dist-info/WHEEL
GooglePatents-0.0.3.dist-info/top_level.txt
GooglePatents-0.0.3.dist-info/RECORD
